PepperPepper/ENVIRO~1.PY
PepperPepper/__init__.py
PepperPepper/cvtest.py
PepperPepper/environment.py
PepperPepper/test.py
PepperPepper/tools.py
PepperPepper/IRSPS/__init__.py
PepperPepper/IRSPS/callbacks/__init__.py
PepperPepper/IRSPS/datasets/__init__.py
PepperPepper/IRSPS/layers/__init__.py
PepperPepper/IRSPS/models/__init__.py
PepperPepper/IRSPS/tools/__init__.py
PepperPepper/IRSTD/__init__.py
PepperPepper/IRSTD/callbacks/__init__.py
PepperPepper/IRSTD/callbacks/trainer.py
PepperPepper/IRSTD/datasets/DG_datasets.py
PepperPepper/IRSTD/datasets/__init__.py
PepperPepper/IRSTD/datasets/datasets.py
PepperPepper/IRSTD/layers/SDifferenceConv.py
PepperPepper/IRSTD/layers/SProb.py
PepperPepper/IRSTD/layers/__init__.py
PepperPepper/IRSTD/models/ACM.py
PepperPepper/IRSTD/models/ALCNet.py
PepperPepper/IRSTD/models/CM2UNet.py
PepperPepper/IRSTD/models/CM2UNetV2.py
PepperPepper/IRSTD/models/DNANet.py
PepperPepper/IRSTD/models/DRPCANet.py
PepperPepper/IRSTD/models/EXEM.py
PepperPepper/IRSTD/models/IRGradOriNet.py
PepperPepper/IRSTD/models/IRSTDNet.py
PepperPepper/IRSTD/models/IRWACV.py
PepperPepper/IRSTD/models/KASSMPCA.py
PepperPepper/IRSTD/models/KASSMPCA_init.py
PepperPepper/IRSTD/models/LSDSSM.py
PepperPepper/IRSTD/models/MLPNet_network.py
PepperPepper/IRSTD/models/MLPnet.py
PepperPepper/IRSTD/models/MSHNet.py
PepperPepper/IRSTD/models/MTransNet.py
PepperPepper/IRSTD/models/PAMUNet.py
PepperPepper/IRSTD/models/PBPCA.py
PepperPepper/IRSTD/models/PCAMAMBA.py
PepperPepper/IRSTD/models/PQGNet.py
PepperPepper/IRSTD/models/RPCANet.py
PepperPepper/IRSTD/models/RPCASSM.py
PepperPepper/IRSTD/models/SCTransNet.py
PepperPepper/IRSTD/models/SegPix.py
PepperPepper/IRSTD/models/UIUNet.py
PepperPepper/IRSTD/models/UNet.py
PepperPepper/IRSTD/models/Unet.py
PepperPepper/IRSTD/models/VMUNet.py
PepperPepper/IRSTD/models/WUNet.py
PepperPepper/IRSTD/models/__init__.py
PepperPepper/IRSTD/models/mim_network.py
PepperPepper/IRSTD/models/resnet.py
PepperPepper/IRSTD/models/AGPCNet/__init__.py
pepperpepper-0.0.9.37.dist-info/METADATA
pepperpepper-0.0.9.37.dist-info/WHEEL
pepperpepper-0.0.9.37.dist-info/top_level.txt
pepperpepper-0.0.9.37.dist-info/zip-safe
pepperpepper-0.0.9.37.dist-info/RECORD
