Metadata-Version: 2.4
Name: PepperPepper
Version: 0.0.9.37
Summary: It is a Deeplearning package to foster developed by Aohua Li
Home-page: 
Author: Aohua Li
Author-email: liah24@mails.jlu.edu.cn
Requires-Python: >=3.7
Dynamic: author
Dynamic: author-email
Dynamic: requires-python
Dynamic: summary
